pylonic/__init__.py
pylonic/api.py
pylonic/autostart.py
pylonic/monitor.py
pylonic/pylonic.py
pylonic/tray.py
pylonic/utils.py
pylon_app-0.9.5.dist-info/LICENSE
pylon_app-0.9.5.dist-info/METADATA
pylon_app-0.9.5.dist-info/WHEEL
pylon_app-0.9.5.dist-info/RECORD
