Metadata-Version: 2.1
Name: pylon-app
Version: 0.9.5
Summary: 
Author: aesthetics-of-record
Author-email: 111675679+aesthetics-of-record@users.noreply.github.com
Requires-Python: >=3.9,<3.13
Classifier: Programming Language :: Python :: 3
Classifier: Programming Language :: Python :: 3.9
Classifier: Programming Language :: Python :: 3.10
Classifier: Programming Language :: Python :: 3.11
Classifier: Programming Language :: Python :: 3.12
Requires-Dist: pyside6 (>=6.7.3,<7.0.0)
